{
"#STAR/SPAEUPBG/-LD/PWA/TPHER": "Star-Spangled Banner",
"#STURPL/UPBD/TKRAEUPBG": "Sturm und Drang",
"#SKWRAEUPB/TKPWO": "Django",
"#SKWRAPB/TKPWO": "",
"#SPAEUPBG/HREURB": "Spanglish",
"#SPAPBG/HREURB": "",
"#SHAEUPB/KAR": "Shankar",
"#SHAEUPBG/HAOEU": "Shanghai",
"#SHAPBG/HAOEU": "",
"#SHAEUPBG/HAOEU/TPHAOES": "Shanghainese",
"#SHAEUPBG": "Shang",
"#SHAPBG": "",
"#SHAEUPB/TKPWREU/HRA": "Shangri-La",
"#SHAPB/TKPWREU/HRA": "",
"#SHAEUPBG/REU/HRA": "Shangri-La",
"#SHAPBG/REU/HRA": "",
"#SHEPB/KWRAEUPBG": "Shenyang",
"#SHEPB/KWRAPBG": "",
"#SHEPB/KWRAEUPBG": "Shenyang",
"#SHEPB/KWRAPBG": "",
"#SAOEUPB/HRAEUPBLG": "Sign Language",
"#SAOEUPB/HRAPBLG": "",
"#SAOEUPB/HRAEUPBG/WAPBLG": "Sign Language",
"#SAOEUPB/HRAPBG/WAPBLG": "",
"#SA*EUPBG/KWREU": "Sankey",
"#TKRAEUPB/TKPWOE": "Durango",
"#TKRAPB/TKPWOE": "",
"#TKUR/KWRAEUPB/TKPWOE": "Durango",
"#TKUR/KWRAPB/TKPWOE": "",
"#TAEUPB/SKWRAOER": "Tangier",
"#TAPB/SKWRAOER": "",
"#TAEUPB/SKWRAOERZ": "Tangiers",
"#TAPB/SKWRAOERZ": "",
"#TAEUPB/SKWREU/KWRER": "Tangier",
"#TAPB/SKWREU/KWRER": "",
"#TAEUPB/SKWREUR": "Tangier",
"#TAPB/SKWREUR": "",
"#TKOEUFP/PWA*EUPBG": "Deutschebank",
"#TKOEUFP/PWA*PBG": "",
"#TPRA*EUPBG": "Frank",
"#TPRA*PBG": "",
"#TPRA*EUPBG/STAR/-LG": "Frank Starling",
"#TPRA*PBG/STAR/-LG": "",
"#TPRA*EUPBG/SEU/TPHA/TRA": "Frank Sinatra",
"#TPRA*PBG/SEU/TPHA/TRA": "",
"#TPRA*EUPBG/SEU/TPHAT/RA": "Frank Sinatra",
"#TPRA*PBG/SEU/TPHAT/RA": "",
"#TPRA*EUPBG/TPRURT": "Frankfurter",
"#TPRA*PBG/TPRURT": "",
"#TPRA*EUPBG/TPO*EPB": "Francophone",
"#TPRA*PBG/TPO*EPB": "",
"#TPRA*EUPBG/TPO*RT": "Frankfort",
"#TPRA*PBG/TPO*RT": "",
"#TPRA*EUPBG/TP*URT": "Frankfurt",
"#TPRA*PBG/TP*URT": "",
"#TPRA*EUPBG/TP*URT/*ER": "Frankfurter",
"#TPRA*PBG/TP*URT/*ER": "",
"#TPRA*EUPBG/TPUR/TER": "Frankfurter",
"#TPRA*PBG/TPUR/TER": "",
"#TPRA*EUPBG/TPURT": "Frankfurt",
"#TPRA*PBG/TPURT": "",
"#TPRA*EUPBG/KWRO": "Franco",
"#TPRA*PBG/KWRO": "",
"#TPRA*EUPBG/KWRO/TPO*EPB": "Francophone",
"#TPRA*PBG/KWRO/TPO*EPB": "",
"#TPRA*EUPBG/KWROE": "Franco",
"#TPRA*PBG/KWROE": "",
"#TPRA*EUPBG/KWROE/TPO*EPB": "Francophone",
"#TPRA*PBG/KWROE/TPO*EPB": "",
"#TPRA*EUPBG/KWREPB/STAOEUPB": "Frankenstein",
"#TPRA*PBG/KWREPB/STAOEUPB": "",
"#TPRA*EUPBG/KWREL": "Frankel",
"#TPRA*PBG/KWREL": "",
"#TPRA*EUPBG/HROEUD/WRAOEUT": "Frank Lloyd Wright",
"#TPRA*PBG/HROEUD/WRAOEUT": "",
"#TPRA*EUPBG/HREUPB": "Franklin",
"#TPRA*PBG/HREUPB": "",
"#TPRA*EUPBG/-BG": "Franck",
"#TPRA*PBG/-BG": "",
"#TPRA*EUPBG/-L": "Frankel",
"#TPRA*PBG/-L": "",
"#TPRAEUPB/KAOE": "Frankie",
"#TPRAPB/KAOE": "",
"#TPRAEUPB/KO": "Franco",
"#TPRAPB/KO": "",
"#TPRAEUPB/KO/TPO*EPB": "Francophone",
"#TPRAPB/KO/TPO*EPB": "",
"#TPRAEUPB/KOE": "Franco",
"#TPRAPB/KOE": "",
"#TPRAEUPB/KOE/TPO*EPB": "Francophone",
"#TPRAPB/KOE/TPO*EPB": "",
"#TPRAEUPB/KEPB/STAOEUPB": "Frankenstein",
"#TPRAPB/KEPB/STAOEUPB": "",
"#TPRAEUPB/KEPB/STAOEPB": "Frankenstein",
"#TPRAPB/KEPB/STAOEPB": "",
"#TPRAEUPB/KEL": "Frankel",
"#TPRAPB/KEL": "",
"#TPRAEUPBG": "Frank",
"#TPRAPBG": "",
"#TPRAEUPBG/STAOEUPB": "Frankenstein",
"#TPRAPBG/STAOEUPB": "",
"#TPRAEUPBG/STAOEPB": "Frankenstein",
"#TPRAPBG/STAOEPB": "",
"#TPRAEUPBG/TPORT": "Frankfort",
"#TPRAPBG/TPORT": "",
"#TPRAEUPBG/KWRO": "Franco",
"#TPRAPBG/KWRO": "",
"#TPRAEUPBG/KWREPB/STAOEPB": "Frankenstein",
"#TPRAPBG/KWREPB/STAOEPB": "",
"#TPRAEUPBG/KO": "Franco",
"#TPRAPBG/KO": "",
"#TPAEUR/PWA*EUPBGS": "Fairbanks",
"#TPRA/HAEUPBG/KWREU/PA/HRA/SREUG": "Frahang-i Pahlavig",
"#THA*EUPBGS": "Thanks",
"#THA*PBGS": "",
"#THA*EUPBGS/TKPW*EUFG": "Thanksgiving",
"#THA*PBGS/TKPW*EUFG": "",
"#THA*EUPBGS/TKPWEUFG": "Thanksgiving",
"#THA*PBGS/TKPWEUFG": "",
"#THAEUPBGS": "Thanks",
"#THAPBGS": "",
"#THAEUPBGS/TKPW*EUFG": "Thanksgiving",
"#THAPBGS/TKPW*EUFG": "",
"#THAEUPBGS/TKPWEUFG": "Thanksgiving",
"#THAPBGS/TKPWEUFG": "",
"#T*D/PWA*EUPBG": "TD Bank",
"#T*D/PWA*PBG": "",
"#KPAEUPBG/KWRA": "Xanga",
"#KWHAEUPB/KAOE": "Yankee",
"#KWHAPB/KAOE": "",
"#KWHAEUPBG": "Yang",
"#KWHAPBG": "",
"#KWHAEUPBG/TKPWOPB": "Yangon",
"#KWHAPBG/TKPWOPB": "",
"#KWHAEUPBG/KWRAOE": "Yankee",
"#KWHAPBG/KWRAOE": "",
"#KWHAEUPBG/KWRAOE/TKAOD/-L": "Yankee Doodle",
"#KWHAEUPBG/KWROPB": "Yangon",
"#KWHAPBG/KWROPB": "",
"#KWHAEUPBG/KAOE": "Yankee",
"#KWHAPBG/KAOE": "",
"#KWHAEUPBG/KAOE/TKAOD/-L": "Yankee Doodle",
"#KWHAEUPBG/SAOE": "Yangtze",
"#KHAEUPBG": "Chang",
"#KHAPBG": "",
"#KRAOUBG/SHA*EUPBG": "Cruikshank",
"#KAEUPBG": "Kang",
"#KAPBG": "",
"#PWHRA*EUPBG/KWREPB/SH*EUP": "Blankenship",
"#PWAEUPB/TKPWA/HROR": "Bangalore",
"#PWAPB/TKPWA/HROR": "",
"#PWAEUPBG/KOG": "Bangkok",
"#PWAPBG/KOG": "",
"#PWAEUPBG/HRA": "Bangla",
"#PWAPBG/HRA": "",
"#PWAEUPBG/HRA/TKERB": "Bangladesh",
"#PWAPBG/HRA/TKERB": "",
"#PWAEUPBG/HROR": "Bangalore",
"#PWAPBG/HROR": "",
"#PWAEUPBG/O*R": "Bangor",
"#PWEUG/PWAEUPBG": "Big Bang",
"#PHA*EUPBGS": "Manx",
"#PHUS/TAEUPBG": "Mustang",
"#PHUS/TAPBG": "",
"#PE/TPHAEUPBG": "Penang",
"#PAOE/KWROPBG/KWRAEUPBG": "Pyongyang",
"#PAOE/KWROPBG/KWRAPBG": "",
"#POPBG/KWRAEUPBG": "Pyongyang",
"#POPBG/KWRAPBG": "",
"#PE/KWROPBG/KWRAEUPBG": "Pyongyang",
"#PE/KWROPBG/KWRAPBG": "",
"#PEU/KWROPBG/KWRAEUPBG": "Pyongyang",
"#PEU/KWROPBG/KWRAPBG": "",
"#PWUR/PWA*EUPBG": "Burbank",
"#PWUR/PWA*PBG": "",
"#WAEUPBG": "Wang",
"#WAPBG": "",
"#WORLD/PWA*EUPBG": "World Bank",
"#WORLD/PWA*PBG": "",
"#WEFT/PWA*EUPBG": "West Bank",
"#WEFT/PWA*PBG": "",
"#WOEFL/TKPWAEUPBG": "Wolfgang",
"#WOEFL/TKPWAPBG": "",
"#WOFL/TKPWAEUPBG": "Wolfgang",
"#WOFL/TKPWAPBG": "",
"#HRA*EUPBG/SHEUR": "Lancashire",
"#HRAEUPB/KA/SHEUR": "Lancashire",
"#HRAEUPB/KAS/TER": "Lancaster",
"#HRAEUPBG": "Lang",
"#HRAPBG": "",
"#HRAEUPBG/STOPB": "Langston",
"#HRAEUPBG/*ER/HAPBS": "Langerhans",
"#HRAEUPBGS/TOPB": "Langston",
"#HRAEUPBG/TKOPB": "Langdon",
"#HRAEUPBG/PHAOUR": "Langmuir",
"#ER/HRAEUPBG": "Erlang",
"#HRAEUPBG/HRA*PBD": "Langland",
"#HRAEUPBG/HREU": "Langley",
"#HA*EUPBG": "Hank",
"#HA*PBG": "",
"#RAEUPB/TKPWAOPB": "Rangoon",
"#RAEUPB/TKPWOE": "Rango",
"#RAPB/TKPWOE": "",
"#RAEUPBG/TKPWAOPB": "Rangoon",
"#RAEUPBG/TKPWOE": "Rango",
"#RAPBG/TKPWOE": "",
"#RAEUPBG/KWRAOPB": "Rangoon",
"#AEUPBG/HROE": "Anglo",
"#APBG/HROE": "",
"#AEUPBG/HROE/SABGS/SOPB": "Anglo-Saxon",
"#APBG/HROE/SABGS/SOPB": "",
"#AEUPBG/HROE/SABGS/OPB": "Anglo-Saxon",
"#APBG/HROE/SABGS/OPB": "",
"#AEUPBG/HREU/KAEUPB": "Anglican",
"#APBG/HREU/KAPB": "",
"#AEUPBG/HREU/KAEUPB/KWREUFPL": "Anglicanism",
"#APBG/HREU/KAPB/KWREUFPL": "",
"#AEUPBG/RAEUPBLG": "Anchorage",
"#APBG/RAPBLG": "",
"#AEUPB/TKPWUS": "Angus",
"#APB/TKPWUS": "",
"#AEUPBG": "Ang",
"#APBG": "",
"#AULD/HRAEUPBG/SAOEUPB": "Auld Lang Syne",
"STRAPBG/HRAEUGS": "",
"STRAPBG/HRAEUT": "",
"STRAPBG/HREUPBG": "",
"STRAPBG/HRER": "",
"STRAPBG/-L": "",
"STRAEUPBG/-L/HO*ELD": "stranglehold",
"STRAPBG/-L/HO*ELD": "",
"STRAPBG/-L/-D": "",
"STRAEUPBG/-L/-Z": "strangles",
"STRAPBG/-LD": "",
"STRAPBG/-LZ": "",
"STA*EUPBG": "stank",
"STA*PBG": "",
"SKWRA*EUPBG": "jank",
"SKWRA*PBG": "",
"SKWRA*EUPBG/KWREU": "janky",
"SKWRA*PBG/KWREU": "",
"SKWRAEUPBG/-L": "jangle",
"SKWRAPBG/-L": "",
"SKWRAEUPBG/-L/-G": "jangling",
"SKWRAEUPBG/-LG": "jangling",
"SKWRAPBG/-LG": "",
"SKWRAEUPBG/-L/-Z": "jangles",
"SKWRAEUPBG/-LZ": "jangles",
"SKWRAEUPBG/-L/-D": "jangled",
"SKWRAEUPBG/-LD": "jangled",
"SKA*EUPBG": "skank",
"SKA*PBG": "",
"TKEU/SEPB/TAEUPBG/-L": "disentangle",
"TKEU/SEPB/TAPBG/-L": "",
"TKEU/SEPB/TAEUPBG/-L/-G": "disentangling",
"TKEU/SEPB/TAPBG/-L/-G": "",
"TKEU/SEPB/TAEUPBG/-LG": "disentangling",
"TKEU/SEPB/TAPBG/-LG": "",
"P*EPBT/AEUPBG/-L": "pentangle",
"P*EPBT/APBG/-L": "",
"PEPB/TA/AEUPBG/-L": "pentangle",
"PEPB/TA/APBG/-L": "",
"PEPB/TAEUPBG/-L": "pentangle",
"PEPB/TAPBG/-L": "",
"EPB/TAEUPBG/-L": "entangle",
"EPB/TAPBG/-L": "",
"EPB/TAEUPBG/-L/-PLT": "entanglement",
"EPB/TAPBG/-L/-PLT": "",
"EPB/TAEUPBG/-L/-G": "entangling",
"EPB/TAPBG/-L/-G": "",
"EPB/TAEUPBG/-LG": "entangling",
"EPB/TAPBG/-LG": "",
"EPB/TAEUPBG/-L/-D": "entangled",
"EPB/TAPBG/-L/-D": "",
"EPB/TAEUPBG/-LD": "entangled",
"EPB/TAPBG/-LD": "",
"EPB/TAEUPBG/-L/-Z": "entangles",
"EPB/TAPBG/-L/-Z": "",
"EPB/TAEUPBG/-LZ": "entangles",
"EPB/TAPBG/-LZ": "",
"SPHRA*EUPBG/TPHEUBG": "splanchnic",
"SPA*EUPBG": "spank",
"SPA*PBG": "",
"SPA*EUPBG/-G": "spanking",
"SPA*PBG/-G": "",
"SPA*EUPBG/-D": "spanked",
"SPA*PBG/-D": "",
"SPA*EUPBG/-Z": "spanks",
"SPA*PBG/-Z": "",
"SPA*EUPBGD": "spanked",
"SPA*PBGD": "",
"SPA*EUPBGZ": "spanks",
"SPA*PBGZ": "",
"SPAEUPBG": "spang",
"SPAPBG": "",
"SPAEUPBG/HRER": "spangler",
"SPAPBG/HRER": "",
"SPAEUPBG/-L": "spangle",
"SPAEUPBG/-L/-G": "spangling",
"SPAEUPBG/-LG": "spangling",
"SPAEUPBG/-L/-D": "spangled",
"SPAEUPBG/-LD": "spangled",
"SPAEUPBG/-L/-Z": "spangles",
"SPAEUPBG/-LZ": "spangles",
"SPRAEUPBG": "sprang",
"SPRAPBG": "",
"SWA*EUPBG": "swank",
"SWA*PBG": "",
"SWA*EUPBG/KWREU/HREU": "swankily",
"SWA*PBG/KWREU/HREU": "",
"SWA*EUPBG/HREU": "swankily",
"SWA*PBG/HREU": "",
"SWA*EUPBG/KWREU": "swanky",
"SWA*PBG/KWREU": "",
"SWA*EUPBG/KWREU/*ER": "swankier",
"SWA*PBG/KWREU/*ER": "",
"SWA*EUPBG/KWRER": "swankier",
"SWA*PBG/KWRER": "",
"SHRA*EUPBG": "shrank",
"SHRA*PBG": "",
"SHRAEUPBG": "slang",
"SHRAPBG": "",
"SHRAEUPBLG": "slanguage",
"SHRAPBLG": "",
"SHRAEUPBG/WAPBLG": "slanguage",
"SHRAPBG/WAPBLG": "",
"SHA*EUPBG": "shank",
"SHA*PBG": "",
"SHA*EUPBG/-Z": "shanks",
"SHA*PBG/-Z": "",
"SHA*EUPBGZ": "shanks",
"SHA*PBGZ": "",
"SHA*EUPBG/KWRER": "chancre",
"SHAEUPBG/HAOEU/-G": "shanghaiing",
"SHAEUPBG/HAOEUG": "shanghaiing",
"SHAEUPBG/HAOEU/-D": "shanghaied",
"SHAEUPBG/HAOEUD": "shanghaied",
"SHAEUPB/TKPWREU/HRA": "shangri-la",
"SHAPB/TKPWREU/HRA": "",
"SHAEUPBG/REU/HRA": "shangri-la",
"SHAPBG/REU/HRA": "",
"SHAU/SHA*EUPBG": "Shawshank",
"SHAU/SHAEUPBG": "Shawshank",
"SHE/PWAEUPBG": "shebang",
"SHE/PWAPBG": "",
"SRAEUPB/KWEURB": "vanquish",
"SRAPB/KWEURB": "",
"SRAEUPBG/KWEURB": "vanquish",
"SRAPBG/KWEURB": "",
"SA*EUPBG": "sank",
"SA*PBG": "",
"SA*EUPBG/TWAEUR/KWREU": "sanctuary",
"SA*PBG/TWAEUR/KWREU": "",
"SA*EUPBG/TWAER": "sanctuary",
"SA*PBG/TWAER": "",
"SA*EUPBG/TEU/TPAOEU": "sanctify",
"SA*PBG/TEU/TPAOEU": "",
"SA*EUPBG/TEU/TPEU/KAEUGS": "sanctification",
"SA*PBG/TEU/TPEU/KAEUGS": "",
"SA*EUPBG/TEU/TEU": "sanctity",
"SA*PBG/TEU/TEU": "",
"SA*EUPBG/TEU/PHOE/TPHEU": "sanctimony",
"SA*PBG/TEU/PHOE/TPHEU": "",
"SA*EUPBG/TEU/PHOE/TPHEU/KWRUS": "sanctimonious",
"SA*PBG/TEU/PHOE/TPHEU/KWRUS": "",
"SA*EUPBG/TEU/PHOEPB": "sanctimony",
"SA*PBG/TEU/PHOEPB": "",
"SA*EUPBG/TEU/PHOEPB/KWRUS": "sanctimonious",
"SA*PBG/TEU/PHOEPB/KWRUS": "",
"SA*EUPBG/TEUT": "sanctity",
"SA*PBG/TEUT": "",
"SA*EUPBG/TUPL": "sanctum",
"SA*PBG/TUPL": "",
"SA*EUPBG/TUS": "sanctus",
"SA*PBG/TUS": "",
"SA*EUPBG/KHAOU/WAEUR/KWREU": "sanctuary",
"SA*PBG/KHAOU/WAEUR/KWREU": "",
"SA*EUPBG/KHAOU/WAER": "sanctuary",
"SA*PBG/KHAOU/WAER": "",
"SA*EUPBGT": "sanct",
"SA*PBGT": "",
"SA*EUPBGT/TPAOEU": "sanctify",
"SA*PBGT/TPAOEU": "",
"SA*EUPBGT/TPAEUBGS": "sanctification",
"SA*PBGT/TPAEUBGS": "",
"SA*EUPBGT/TPEU/KAEUGS": "sanctification",
"SA*PBGT/TPEU/KAEUGS": "",
"SA*EUPBGT/TEU": "sanctity",
"SA*PBGT/TEU": "",
"SA*EUPBGT/PHOE/TPHEU": "sanctimony",
"SA*PBGT/PHOE/TPHEU": "",
"SA*EUPBGT/PHOEPB": "sanctimony",
"SA*PBGT/PHOEPB": "",
"SA*EUPBGT/PHOEPB/KWRUS": "sanctimonious",
"SA*PBGT/PHOEPB/KWRUS": "",
"SA*EUPBGS": "sanction",
"SA*PBGS": "",
"SAEUPBG": "sang",
"SAPBG": "",
"SAEUPBG/TKPWREU/KWRA": "sangria",
"SAPBG/TKPWREU/KWRA": "",
"SAEUPBG/TKPWREU/HROE": "sangrillo",
"SAPBG/TKPWREU/HROE": "",
"SAEUPBG/TPRO*EUD": "sangfroid",
"SAPBG/TPRO*EUD": "",
"SAEUPBG/TWAEUR/KWREU": "sanctuary",
"SAPBG/TWAEUR/KWREU": "",
"SAEUPBG/TWAER": "sanctuary",
"SAPBG/TWAER": "",
"SAEUPBG/TEU/TPAOEU": "sanctify",
"SAPBG/TEU/TPAOEU": "",
"SAEUPBG/TEU/TPAOEU/*ER": "sanctifier",
"SAEUPBG/TEU/TPAOEU/*ER/-Z": "sanctifiers",
"SAEUPBG/TEU/TPAOEU/*ERZ": "sanctifiers",
"SAEUPBG/TEU/TPEU/KAEUGS": "sanctification",
"SAPBG/TEU/TPEU/KAEUGS": "",
"SAEUPBG/TEU/TEU": "sanctity",
"SAPBG/TEU/TEU": "",
"SAEUPBG/TEU/PHOE/TPHEU": "sanctimony",
"SAPBG/TEU/PHOE/TPHEU": "",
"SAEUPBG/TEU/PHOE/TPHEU/KWRUS": "sanctimonious",
"SAPBG/TEU/PHOE/TPHEU/KWRUS": "",
"SAEUPBG/TEU/PHOEPB": "sanctimony",
"SAPBG/TEU/PHOEPB": "",
"SAEUPBG/TEU/PHOEPB/KWRUS": "sanctimonious",
"SAPBG/TEU/PHOEPB/KWRUS": "",
"SAEUPBG/TEUT": "sanctity",
"SAPBG/TEUT": "",
"SAEUPBG/TUPL": "sanctum",
"SAPBG/TUPL": "",
"SAEUPBG/TUS": "sanctus",
"SAPBG/TUS": "",
"SAEUPBG/KHAOU/WAEUR/KWREU": "sanctuary",
"SAPBG/KHAOU/WAEUR/KWREU": "",
"SAEUPBG/KHAOU/WAER": "sanctuary",
"SAPBG/KHAOU/WAER": "",
"SAEUPBG/WEU/TPHAEUR/KWREU": "sanguinary",
"SAPBG/WEU/TPHAEUR/KWREU": "",
"SAEUPBG/WEU/TPHAER": "sanguinary",
"SAPBG/WEU/TPHAER": "",
"SAEUPBG/WEUPB": "sanguine",
"SAPBG/WEUPB": "",
"SAEUPBG/WEUPB/KWRAEUR/KWREU": "sanguinary",
"SAPBG/WEUPB/KWRAEUR/KWREU": "",
"SAEUPBG/WEUPB/KWRAER": "sanguinary",
"SAPBG/WEUPB/KWRAER": "",
"SAEUPBG/WEUPB/KWRUS": "sanguineous",
"SAPBG/WEUPB/KWRUS": "",
"SAEUPBG/REU/KWRA": "sangria",
"SAPBG/REU/KWRA": "",
"SAEUPBG/REU/HROE": "sangrillo",
"SAPBG/REU/HROE": "",
"SAEUPBGT/TEU": "sanctity",
"SAPBGT/TEU": "",
"SAEUPBGT/PHOE/TPHEU": "sanctimony",
"SAPBGT/PHOE/TPHEU": "",
"SAEUPBGT/PHOEPB": "sanctimony",
"SAPBGT/PHOEPB": "",
"SAEUPBGS": "sanction",
"SAPBGS": "",
"SARBG/SA*EUPBGT": "sacrosanct",
"SARBG/SA*PBGT": "",
"SARBG/SAEUPBGT": "sacrosanct",
"SARBG/SAPBGT": "",
"SA/KRO/SA*EUPBGT": "sacrosanct",
"SA/KRO/SA*PBGT": "",
"SA/KRO/SAEUPBGT": "sacrosanct",
"SA/KRO/SAPBGT": "",
"SA/KROE/SA*EUPBGT": "sacrosanct",
"SA/KROE/SA*PBGT": "",
"SA/KROE/SAEUPBGT": "sacrosanct",
"SA/KROE/SAPBGT": "",
"TKPWAEUPB/TKPWRAOE/TPHUS": "gangrenous",
"TKPWAPB/TKPWRAOE/TPHUS": "",
"TKPWAEUPB/TKPWRAOEPB": "gangrene",
"TKPWAPB/TKPWRAOEPB": "",
"TKPWAEUPB/RAOE/TPHOE/SUPL": "gangrenosum",
"TKPWAPB/RAOE/TPHOE/SUPL": "",
"TKPWAEUPBG": "gang",
"TKPWAPBG": "",
"TKPWAEUPBG/STA": "gangsta",
"TKPWAPBG/STA": "",
"TKPWAEUPBG/STER": "gangster",
"TKPWAPBG/STER": "",
"TKPWAEUPBG/STER/-Z": "gangsters",
"TKPWAPBG/STER/-Z": "",
"TKPWAEUPBG/STERZ": "gangsters",
"TKPWAPBG/STERZ": "",
"TKPWAEUPBG/TKPWRAOE/TPHOE/SUPL": "gangrenosum",
"TKPWAPBG/TKPWRAOE/TPHOE/SUPL": "",
"TKPWAEUPBG/TKPWRAOE/TPHUS": "gangrenous",
"TKPWAPBG/TKPWRAOE/TPHUS": "",
"TKPWAEUPBG/TKPWRAOEPB": "gangrene",
"TKPWAPBG/TKPWRAOEPB": "",
"TKPWAEUPBG/PHRA*PBG": "gangplank",
"TKPWAPBG/PHRA*PBG": "",
"TKPWAEUPBG/PHRA*PBG/-Z": "gangplanks",
"TKPWAPBG/PHRA*PBG/-Z": "",
"TKPWAEUPBG/PHRA*PBGZ": "gangplanks",
"TKPWAPBG/PHRA*PBGZ": "",
"TKPWAEUPBG/HREU/KWRA": "ganglia",
"TKPWAPBG/HREU/KWRA": "",
"TKPWAEUPBG/HREU/KWRO/SAOEUD": "ganglioside",
"TKPWAPBG/HREU/KWRO/SAOEUD": "",
"TKPWAEUPBG/HREU/KWROE/SAOEUD": "ganglioside",
"TKPWAPBG/HREU/KWROE/SAOEUD": "",
"TKPWAEUPBG/HREU/KWROPB": "ganglion",
"TKPWAPBG/HREU/KWROPB": "",
"TKPWAEUPBG/HREU/KWROPB/KWREUBG": "ganglionic",
"TKPWAPBG/HREU/KWROPB/KWREUBG": "",
"TKPWAEUPBG/RAOE/TPHOE/SUPL": "gangrenosum",
"TKPWAPBG/RAOE/TPHOE/SUPL": "",
"TKPWAEUPBG/RAOE/TPHUS": "gangrenous",
"TKPWAPBG/RAOE/TPHUS": "",
"TKPWAEUPBG/RAOEPB": "gangrene",
"TKPWAPBG/RAOEPB": "",
"TKPWAEUPBG/-D": "ganged",
"TKPWAPBG/-D": "",
"TKPWAEUPBG/-Z": "gangs",
"TKPWAPBG/-Z": "",
"TKPWAEUPBGS/TA": "gangsta",
"TKPWAPBGS/TA": "",
"TKPWAEUPBGS/TER": "gangster",
"TKPWAPBGS/TER": "",
"TKPWAEUPBGS/TER/-Z": "gangsters",
"TKPWAPBGS/TER/-Z": "",
"TKPWAEUPBGS/TERZ": "gangsters",
"TKPWAPBGS/TERZ": "",
"TKPWAEUPBGD": "ganged",
"TKPWAPBGD": "",
"TKPWAEUPBGZ": "gangs",
"TKPWAPBGZ": "",
"TKPWAEUPBG/HREU": "gangly",
"TKRA*EUPBG": "drank",
"TKRA*PBG": "",
"TKA*EUPBG": "dank",
"TKA*PBG": "",
"TKAEUPBG": "dang",
"TKAPBG": "",
"TKAEUPBG/KWREUT": "dangit",
"TKAPBG/KWREUT": "",
"TKAEUPBG/-L": "dangle",
"TKAPBG/-L": "",
"TKAEUPBG/-L/-G": "dangling",
"TKAPBG/-L/-G": "",
"TKAEUPBG/-L/-D": "dangled",
"TKAPBG/-L/-D": "",
"TKAEUPBG/-LG": "dangling",
"TKAPBG/-LG": "",
"TKAEUPBG/-LD": "dangled",
"TKAPBG/-LD": "",
"TKAEUPBG/-LZ": "dangles",
"TKAPBG/-LZ": "",
"TKAEUPBGT": "dangit",
"TKAPBGT": "",
"TKO/PEL/TKPWAEURPBG": "doppelgänger",
"TKO/PEL/TKPWARPBG": "",
"TKO/PEL/TKPWAEUPB/TKPWER": "doppelgänger",
"TKO/PEL/TKPWAPB/TKPWER": "",
"TKO/PEL/TKPWAEUPBG/TKPWER": "doppelgänger",
"TKO/PEL/TKPWAPBG/TKPWER": "",
"TKO/PEL/TKPWAEUPBG/KWRER": "doppelgänger",
"TKO/PEL/TKPWAPBG/KWRER": "",
"TKO/PEL/TKPWAEUPBG/*ER": "doppelgänger",
"TKO/PEL/TKPWAPBG/*ER": "",
"TKOPL/TKPWAEURPBG": "doppelgänger",
"TKOPL/TKPWARPBG": "",
"TPHRA*EUPBG": "flank",
"TPHRA*PBG": "",
"TPHRA*EUPBG/-G": "flanking",
"TPHRA*PBG/-G": "",
"TPHRA*EUPBG/-D": "flanked",
"TPHRA*PBG/-D": "",
"TPHRA*EUPBG/-Z": "flanks",
"TPHRA*PBG/-Z": "",
"TPHRA*EUPBGD": "flanked",
"TPHRA*PBGD": "",
"TPHRA*EUPBGZ": "flanks",
"TPHRA*PBGZ": "",
"TPHAOU/TKEU/PWRAEUFRPB": "nudibranch",
"TPHAOUD/PWRAEUFRPB": "nudibranch",
"TPHU/TPA*EUPBG": "newfang",
"TPHU/TPA*PBG": "",
"TPHU/TPA*EUPBG/-L": "newfangle",
"TPHU/TPA*EUPBG/-LD": "newfangled",
"TPHU/TPA*PBG/-LD": "",
"TPRA*EUPBG": "frank",
"TPRA*PBG": "",
"TPRA*EUPBG/KWREUPB/SEPBS": "frankincense",
"TPRA*EUPBG/KWRAOE": "frankie",
"TPRA*PBG/KWRAOE": "",
"TPRA*EUPBG/HREU": "frankly",
"TPRA*PBG/HREU": "",
"TPRA*EUPBG/-PBS": "frankness",
"TPRA*PBG/-PBS": "",
"TPRA*EUPBG/-Z": "franks",
"TPRA*PBG/-Z": "",
"TPRA*EUPBGZ": "franks",
"TPRA*PBGZ": "",
"TPRAEUBG": "franc",
"TPRAPBG": "",

"TPAEUPBG/-L": "fangle",
"TPAPB/TKAEUPB/TKPWO": "fandango",
"TPAPB/TKAPB/TKPWO": "",
"TPAPB/TKAEUPB/TKPWOE": "fandango",
"TPAPB/TKAPB/TKPWOE": "",
"TPAPB/TKAEUPBG/TKPWO": "fandango",
"TPAPB/TKAPBG/TKPWO": "",
"TPAPB/TKAEUPBG/TKPWOE": "fandango",
"TPAPB/TKAPBG/TKPWOE": "",
"TWAEUPBG": "twang",
"TWAPBG": "",
"THA*EUPBG": "thank",
"THA*PBG": "",
"THA*EUPBG/-FL": "thankful",
"THA*PBG/-FL": "",
"THA*EUPBG/-G": "thanking",
"THA*PBG/-G": "",
"THA*EUPBGD": "thanked",
"THA*PBGD": "",
"THA*EUPBGZ": "thanks",
"THA*PBGZ": "",

"TRA*EUPBG/HRAOEURSZ": "tranquilizers",
"TRA*PBG/HRAOEURSZ": "",
"TRA*EUPBG/HRAOEURZ": "tranquilizer",
"TRA*PBG/HRAOEURZ": "",
"TRA*EUPBG/HRAOEUGZ": "tranquilizing",
"TRA*PBG/HRAOEUGZ": "",
"TRA*EUPBG/HRAOEUSZ": "tranquilizes",
"TRA*PBG/HRAOEUSZ": "",
"TRA*EUPBG/HRAOEUDZ": "tranquilized",
"TRA*PBG/HRAOEUDZ": "",
"TRA*EUPBG/HRAOEUZ": "tranquilize",
"TRA*PBG/HRAOEUZ": "",
"TRA*EUPBG/HRAOEUZ/-D": "tranquilized",
"TRA*PBG/HRAOEUZ/-D": "",
"TRAEUPB/KWEU/HREU": "tranquilly",
"TRAEUPB/KWEUL": "tranquil",
"TRAPB/KWEUL": "",
"TRAEUPB/KWEUL/TEU": "tranquility",
"TRAPB/KWEUL/TEU": "",
"TRAEUPB/KWEUL/KWRAOEURSZ": "tranquilizers",
"TRAPB/KWEUL/KWRAOEURSZ": "",
"TRAEUPB/KWEUL/KWRAOEURZ": "tranquilizer",
"TRAPB/KWEUL/KWRAOEURZ": "",
"TRAEUPB/KWEUL/KWRAOEUGZ": "tranquilizing",
"TRAPB/KWEUL/KWRAOEUGZ": "",
"TRAEUPB/KWEUL/KWRAOEUSZ": "tranquilizes",
"TRAPB/KWEUL/KWRAOEUSZ": "",
"TRAEUPB/KWEUL/KWRAOEUDZ": "tranquilized",
"TRAPB/KWEUL/KWRAOEUDZ": "",
"TRAEUPB/KWEUL/KWRAOEUZ": "tranquilize",
"TRAPB/KWEUL/KWRAOEUZ": "",
"TRAEUPB/KWEUL/KWRAOEUZ/-D": "tranquilized",
"TRAPB/KWEUL/KWRAOEUZ/-D": "",
"TRAEUPB/KWEULT": "tranquility",
"TRAPB/KWEULT": "",
"TRAEUPBG/KWEU/HREU": "tranquilly",
"TRAEUPBG/KWEUL": "tranquil",
"TRAPBG/KWEUL": "",
"TRAEUPBG/KWEUL/TEU": "tranquility",
"TRAPBG/KWEUL/TEU": "",
"TRAEUPBG/KWEUL/KWRAOEURSZ": "tranquilizers",
"TRAPBG/KWEUL/KWRAOEURSZ": "",
"TRAEUPBG/KWEUL/KWRAOEURZ": "tranquilizer",
"TRAPBG/KWEUL/KWRAOEURZ": "",
"TRAEUPBG/KWEUL/KWRAOEUGZ": "tranquilizing",
"TRAPBG/KWEUL/KWRAOEUGZ": "",
"TRAEUPBG/KWEUL/KWRAOEUSZ": "tranquilizes",
"TRAPBG/KWEUL/KWRAOEUSZ": "",
"TRAEUPBG/KWEUL/KWRAOEUDZ": "tranquilized",
"TRAPBG/KWEUL/KWRAOEUDZ": "",
"TRAEUPBG/KWEUL/KWRAOEUZ": "tranquilize",
"TRAPBG/KWEUL/KWRAOEUZ": "",
"TRAEUPBG/KWEUL/KWRAOEUZ/*ER": "tranquilizer",
"TRAPBG/KWEUL/KWRAOEUZ/*ER": "",
"TRAEUPBG/KWEUL/KWRAOEUZ/*ER/-Z": "tranquilizers",
"TRAPBG/KWEUL/KWRAOEUZ/*ER/-Z": "",
"TRAEUPBG/KWEUL/KWRAOEUZ/*ERZ": "tranquilizers",
"TRAPBG/KWEUL/KWRAOEUZ/*ERZ": "",
"TRAEUPBG/KWEUL/KWRAOEUZ/-D": "tranquilized",
"TRAPBG/KWEUL/KWRAOEUZ/-D": "",
"TRAEUPBG/KWEULT": "tranquility",
"TRAPBG/KWEULT": "",
"TA*EUPBG": "tank",
"TA*PBG": "",
"TA*EUPBG/KWRARD": "tankard",
"TA*PBG/KWRARD": "",
"TA*EUPBG/KWRARD/-Z": "tankards",
"TA*PBG/KWRARD/-Z": "",
"TA*EUPBG/KWRARDZ": "tankards",
"TA*PBG/KWRARDZ": "",
"TA*EUPBG/*ER": "tanker",
"TA*PBG/*ER": "",
"TA*EUPBG/*ER/-Z": "tankers",
"TA*PBG/*ER/-Z": "",
"TA*EUPBG/*ERZ": "tankers",
"TA*PBG/*ERZ": "",
"TA*EUPBG/-Z": "tanks",
"TA*PBG/-Z": "",
"TA*EUPBGZ": "tanks",
"TA*PBGZ": "",
"TAEUPB/KARD": "tankard",
"TAPB/KARD": "",
"TH*EUPBG/TA*EUPBG": "thinktank",
"TH*EUPBG/TA*PBG": "",
"THEU/TA*EUPBG": "thinktank",
"THEU/TA*PBG": "",
"TA*EUPBG/TOP": "tanktop",
"TAEUPB/TKPWOE": "tango",
"TAPB/TKPWOE": "",
"TAEUPBG": "tang",
"TAPBG": "",
"TAEUPBG/TKPWOE": "tango",
"TAPBG/TKPWOE": "",
"TAEUPBG/KWREU": "tangy",
"TAPBG/KWREU": "",
"TAEUPBG/KWREU/-PBS": "tanginess",
"TAPBG/KWREU/-PBS": "",
"TAEUPBG/-L": "tangle",
"TAPBG/-L": "",
"TAEUPBG/-L/-G": "tangling",
"TAPBG/-L/-G": "",
"TAEUPBG/-L/-D": "tangled",
"TAPBG/-L/-D": "",
"TAEUPBG/-L/-Z": "tangles",
"TAPBG/-L/-Z": "",
"TAEUPBG/-LG": "tangling",
"TAPBG/-LG": "",
"TAEUPBG/-LD": "tangled",
"TAPBG/-LD": "",
"TAEUPBG/-LZ": "tangles",
"TAPBG/-LZ": "",
"EPL/PWA*EUPBG/-PLT": "embankment",
"EPL/PWA*PBG/-PLT": "",
"EPL/PWA*EUPBG": "embank",
"KWHA*EUPBG": "yank",
"KWHA*PBG": "",
"KWHA*EUPBG/-G": "yanking",
"KWHA*PBG/-G": "",
"KWHA*EUPBG/-D": "yanked",
"KWHA*PBG/-D": "",
"KWHA*EUPBG/-Z": "yanks",
"KWHA*PBG/-Z": "",
"KWHA*EUPBGD": "yanked",
"KWHA*PBGD": "",
"KWHA*EUPBGZ": "yanks",
"KWHA*PBGZ": "",
"KWHAEUPBG": "yang",
"KWHAPBG": "",
"KWHEUPB/KWHA*EUPBG": "yin-yang",
"KWHEUPB/KWHA*PBG": "",
"KWHEUPB/KWRAEUPBG": "yin-yang",
"KWHEUPB/KWRAPBG": "",
"KHRA*EUPBG": "clank",
"KHRA*PBG": "",
"KHRAEUPBG": "clang",
"KHRAPBG": "",
"KHRAEUPBG/O*R": "clangor",
"KHRAPBG/O*R": "",
"KHRAEUPBG/O*R/KWRUS": "clangorous",
"HAEUPBG/*ER": "hanger",
"HAPBG/*ER": "",
"HAEUPBG/*ER/-Z": "hangers",
"HAPBG/*ER/-Z": "",
"HAEUPBG/*ERZ": "hangers",
"HAPBG/*ERZ": "",
"HAEUPBG/-G": "hanging",
"HAPBG/-G": "",
"HAEUPBG/-G/WA*UL": "hangingwall",
"HAPBG/-G/WA*UL": "",
"HAEUPBG/-D": "hanged",
"HAPBG/-D": "",
"HAEUPBG/-Z": "hangs",
"HAPBG/-Z": "",
"HAEUPBGD": "hanged",
"HAPBGD": "",
"HAEUPBGZ": "hangs",
"HAPBGZ": "",
"KHREUF/HA*EUPBG/*ER": "cliffhanger",
"KHREUF/HA*EUPBG/*ER/Z": "cliffhanger",
"KHREUF/HA*EUPBG/*ERZ": "cliffhanger",
"KRA*PBG/SHA*FT": "",
"KA*EUPBG/RUS": "cankerous",
"KA*PBG/RUS": "",
"KAEUPB/KRUS": "cankerous",
"KAPB/KRUS": "",
"KAEUPB/KER": "canker",
"KAPB/KER": "",
"KAEUPB/KER/KWRUS": "cankerous",
"KAPB/KER/KWRUS": "",
"KAEUPB/KER/-Z": "cankers",
"KAPB/KER/-Z": "",
"KAEUPB/KERZ": "cankers",
"KAPB/KERZ": "",
"KAEUPBG/KER": "canker",
"KAPBG/KER": "",
"KAEUPBG/KER/KWRUS": "cankerous",
"KAPBG/KER/KWRUS": "",
"KAEUPBG/KER/-Z": "cankers",
"KAPBG/KER/-Z": "",
"KAEUPBG/KERZ": "cankers",
"KAPBG/KERZ": "",
"KAEUPBG/RAO": "kangaroo",
"KAPBG/RAO": "",
"KOPB/HRAEUPBG": "conlang",
"KAPB/TA*EUPBG/RUS": "cantankerous",
"PWHRA*EUPBG": "blank",
"PWHRA*PBG": "",
"PWHRA*EUPBG/TEU": "blankity",
"PWHRA*PBG/TEU": "",
"PWHRA*EUPBG/TEU/PWHRA*EUPBG": "blankity-blank",
"PWHRA*PBG/TEU/PWHRA*PBG": "",
"PWHRA*EUPBG/KWREFT": "blankest",
"PWHRA*PBG/KWREFT": "",
"PWHRA*EUPBG/KWRET": "blanket",
"PWHRA*PBG/KWRET": "",
"PWHRA*EUPBG/KWRET/-Z": "blankets",
"PWHRA*PBG/KWRET/-Z": "",
"PWHRA*EUPBG/KWRETS": "blankets",
"PWHRA*PBG/KWRETS": "",
"PWHRA*EUPBG/HREU": "blankly",
"PWHRA*PBG/HREU": "",
"PWHRA*EUPBG/*ER": "blanker",
"PWHRA*PBG/*ER": "",
"PWHRA*EUPBG/-G": "blanking",
"PWHRA*PBG/-G": "",
"PWHRA*EUPBG/-D": "blanked",
"PWHRA*PBG/-D": "",
"PWHRA*EUPBG/-Z": "blanks",
"PWHRA*PBG/-Z": "",
"PWHRA*EUPBGD": "blanked",
"PWHRA*PBGD": "",
"PWHRA*EUPBGZ": "blanks",
"PWHRA*PBGZ": "",
"PWHRAEUPB/KET": "blanket",
"PWHRAPB/KET": "",
"PWHRAEUPB/KET/-Z": "blankets",
"PWHRAPB/KET/-Z": "",
"PWHRAEUPB/KETS": "blankets",
"PWHRAPB/KETS": "",
"PWHRAEUPBG/KET": "blanket",
"PWHRAPBG/KET": "",
"PWHRAEUPBG/KET/-Z": "blankets",
"PWHRAPBG/KET/-Z": "",
"PWHRAEUPBG/KETS": "blankets",
"PWHRAPBG/KETS": "",
"POEUPBT/PWHRA*EUPBG": "point-blank",
"POEUPBT/PWHRA*PBG": "",
"PWRAEUFRPB/KWRAL": "branchial",
"PWRAFRPB/KWRAL": "",
"PWAO/PHER/A*EUPBG": "boomerang",
"PWAO/PHER/A*PBG": "",
"PWAO/PHER/AEUPBG": "boomerang",
"PWAO/PHER/APBG": "",
"PWAORPL/KWRAEUPBG": "boomerang",
"PWAORPL/KWRAPBG": "",
"PWAOPL/RAEUPBG": "boomerang",
"PWAOPL/RAPBG": "",
"PWAOPL/*ER/KWRAEUPBG": "boomerang",
"PWAOPL/*ER/KWRAPBG": "",
"PWA*EUPBG": "bank",
"PWA*PBG": "",
"PWA*EUPBG/PWAO*BG": "bankbook",
"PWA*PBG/PWAO*BG": "",
"PWA*EUPBG/TPHO*ET": "banknote",
"PWA*EUPBG/RO*L": "bankroll",
"PWA*PBG/RO*L": "",
"PWA*EUPBG/ROL": "bankroll",
"PWA*PBG/ROL": "",
"PWA*EUPBG/RUPT": "bankrupt",
"PWA*PBG/RUPT": "",
"PWA*EUPBG/RUPT/SEU": "bankruptcy",
"PWA*PBG/RUPT/SEU": "",
"PWA*EUPBG/RUPT/SEU/-Z": "bankruptcies",
"PWA*PBG/RUPT/SEU/-Z": "",
"PWA*EUPBG/RUPT/SEUZ": "bankruptcies",
"PWA*PBG/RUPT/SEUZ": "",
"PWA*EUPBG/*ER": "banker",
"PWA*PBG/*ER": "",
"PWA*EUPBG/*ER/-Z": "bankers",
"PWA*PBG/*ER/-Z": "",
"PWA*EUPBG/*ERZ": "bankers",
"PWA*PBG/*ERZ": "",
"PWA*EUPBG/-BL": "bankable",
"PWA*PBG/-BL": "",
"PWA*EUPBG/-G": "banking",
"PWA*PBG/-G": "",
"PWA*EUPBG/-D": "banked",
"PWA*PBG/-D": "",
"PWA*EUPBG/-Z": "banks",
"PWA*PBG/-Z": "",
"PWA*EUPBGD": "banked",
"PWA*PBGD": "",
"PWA*EUPBGZ": "banks",
"PWA*PBGZ": "",
"PEUG/KWREU/PWA*EUPBG": "piggybank",
"PEUG/KWREU/PWA*PBG": "",
"REUFR/PWA*EUPBG": "riverbank",
"REUFR/PWA*PBG": "",
"PWAEUPB/KW*ET": "banquette",
"PWAPB/KW*ET": "",
"PWAEUPB/KWET": "banquet",
"PWAPB/KWET": "",
"PWAEUPBG/KW*ET": "banquette",
"PWAPBG/KW*ET": "",
"PWAEUPBG/KWET": "banquet",
"PWAPBG/KWET": "",
"PWAEUPBG/-L": "bangle",
"PWAPBG/-L": "",
"PWAEUPBG/-L/-D": "bangled",
"PWAPBG/-L/-D": "",
"PWAEUPBG/-L/-Z": "bangles",
"PWAPBG/-L/-Z": "",
"PWAEUPBG/-LD": "bangled",
"PWAPBG/-LD": "",
"PWAEUPBG/-LZ": "bangles",
"PWAPBG/-LZ": "",
"PWAEUPBG/-D": "banged",
"PWAPBG/-D": "",
"PWAEUPBGD": "banged",
"PWAPBGD": "",
"PWAEUPBG": "bang",
"PWAPBG": "",
"EURPBT/KWRO/PWAEUPBG": "interrobang",
"EURPBT/KWRO/PWAPBG": "",
"EURPBT/KWROE/PWAEUPBG": "interrobang",
"EURPBT/KWROE/PWAPBG": "",
"EURPBT/PWAEUPBG": "interrobang",
"EURPBT/PWAPBG": "",
"EURPBT/RO/PWAEUPBG": "interrobang",
"EURPBT/RO/PWAPBG": "",
"EURPBT/ROE/PWAEUPBG": "interrobang",
"EURPBT/ROE/PWAPBG": "",
"EUPB/TER/KWRO/PWAEUPBG": "interrobang",
"EUPB/TER/KWRO/PWAPBG": "",
"EUPB/TER/KWROE/PWAEUPBG": "interrobang",
"EUPB/TER/KWROE/PWAPBG": "",
"EUPB/TER/PWAEUPBG": "interrobang",
"EUPB/TER/PWAPBG": "",
"EUPB/TER/RO/PWAEUPBG": "interrobang",
"EUPB/TER/RO/PWAPBG": "",
"EUPB/TER/ROE/PWAEUPBG": "interrobang",
"EUPB/TER/ROE/PWAPBG": "",
"PHRA*EUPBG": "plank",
"PHRA*PBG": "",
"PHRA*EUPBG/TO*PB": "plankton",
"PHRA*PBG/TO*PB": "",
"PHRA*EUPBG/TOPB": "plankton",
"PHRA*PBG/TOPB": "",
"PHRA*EUPBG/-G": "planking",
"PHRA*PBG/-G": "",
"PHRAEUPBG/K-G": "planking",
"PHRAPBG/K-G": "",
"TKPWAPBG/PHRA*EUPBG": "gangplank",
"TKPWAPBG/PHRA*PBG": "",
"TKPWAPBG/PHRA*EUPBG/-Z": "gangplanks",
"TKPWAPBG/PHRA*PBG/-Z": "",
"TKPWAPBG/PHRA*EUPBGZ": "gangplanks",
"TKPWAPBG/PHRA*PBGZ": "",
"PHAEUPB/TKPWA/TPHAOES": "manganese",
"PHAPB/TKPWA/TPHAOES": "",
"PHAEUPBG/TKPWA/TPHAOES": "manganese",
"PHAPBG/TKPWA/TPHAOES": "",
"PHAEUPBG/TPHAOES": "manganese",
"PHAPBG/TPHAOES": "",
"PHAEUPB/TKPWOE": "mango",
"PHAPB/TKPWOE": "",
"PHAEUPBG/TKPWOE": "mango",
"PHAPBG/TKPWOE": "",
"PHAEUPBG/HRER": "mangler",
"PHAPBG/-L": "mangle",
"PHAPBG/-L/-G": "mangling",
"PHAPBG/-L/-D": "mangled",
"PHAPBG/-L/-Z": "mangles",
"PHAPBG/-LG": "mangling",
"PHAPBG/-LD": "mangled",
"PHAPBG/-LZ": "mangles",
"PHER/KWRAEUPBG": "meringue",
"PHER/KWRAPBG": "",
"PHER/KWREUPBG": "",
"PHUS/TAEUPBG": "mustang",
"PRA*EUPBG": "prank",
"PRA*PBG": "",
"PRA*EUPBG/STER": "prankster",
"PRA*PBG/STER": "",
"PRA*EUPBG/-Z": "pranks",
"PRA*PBG/-Z": "",
"PRA*EUPBGS/TER": "prankster",
"PRA*PBGS/TER": "",
"PRA*EUPBGZ": "pranks",
"PRA*PBGZ": "",
"PAEUPB/KRAOE/TAOEUTS": "pancreatitis",
"PAEUPB/KRAOE/TEUBG": "pancreatic",
"PAEUPB/KRAOE/KWRA/TAOEU/TEUS": "pancreatitis",
"PAEUPB/KRAOE/KWRA/TEUBG": "pancreatic",
"PAEUPB/KRAOE/KWRAS": "pancreas",
"PAEUPB/KRAOEL": "pancreal",
"PAEUPB/KRAOES": "pancreas",
"PAEUPB/KOE": "panko",
"PAPB/KOE": "",
"PAEUPBG/KOE": "panko",
"PAPBG/KOE": "",
"HA*EUPBG/KWREU/PA*EUPBG/KWREU": "hanky-panky",
"HA*PBG/KWREU/PA*PBG/KWREU": "",
"PAEUPBG": "pang",
"PAPBG": "",
"WRAEUPB/TKPW-L": "wrangle",
"WRAPB/TKPW-L": "",
"WRAEUPBG/TKPW-L": "wrangle",
"WRAPBG/TKPW-L": "",
"WRAEUPBG/TKPW-LD": "wrangled",
"WRAPBG/TKPW-LD": "",
"WRAEUPBG/HRER": "wrangler",
"WRAPBG/HRER": "",
"WRAEUPBG/-L": "wrangle",
"WRAPBG/-L": "",
"WRAEUPBG/-L/*ER": "wrangler",
"WRAPBG/-L/*ER": "",
"WRAEUPBG/-L/-G": "wrangling",
"WRAPBG/-L/-G": "",
"WRAEUPBG/-L/-Z": "wrangles",
"WRAPBG/-L/-Z": "",
"WRAEUPBG/-LG": "wrangling",
"WRAPBG/-LG": "",
"WRAEUPBG/-LD": "wrangled",
"WRAPBG/-LD": "",
"WRAEUPBG/-LZ": "wrangles",
"WRAPBG/-LZ": "",
"WA*EUPBG": "wank",
"WA*PBG": "",
"WA*EUPBG/*ER": "wanker",
"WA*PBG/*ER": "",
"HRA*EUPBG": "lank",
"HRA*PBG": "",
"HRA*EUPBG/KWREU": "lanky",
"HRA*PBG/KWREU": "",
"HRA*EUPBG/KWREU/KWREFT": "lankiest",
"HRA*PBG/KWREU/KWREFT": "",
"HRA*EUPBG/KWREU/HREU": "lankily",
"HRA*PBG/KWREU/HREU": "",
"HRA*EUPBG/KWREU/*ER": "lankier",
"HRA*PBG/KWREU/*ER": "",
"HRA*EUPBG/KWREU/-PBS": "lankiness",
"HRA*PBG/KWREU/-PBS": "",
"HRA*EUPBG/KWRER": "lankier",
"HRA*PBG/KWRER": "",
"HRA*EUPBG/KWRET": "lankiest",
"HRA*PBG/KWRET": "",
"HRA*EUPBG/HREU": "lankily",
"HRA*PBG/HREU": "",
"HRA*EUPBG/-PBS": "lankiness",
"HRA*PBG/-PBS": "",
"HRAEUPBLG": "language",
"HRAPBLG": "",
"HRAEUPBLG/-Z": "languages",
"HRAPBLG/-Z": "",
"HRAEUPBLGZ": "languages",
"HRAPBLGZ": "",
"HRAEUPBG": "lang",
"HRAPBG": "",
"HRAEUPBG/WAPBLG": "language",
"HRAPBG/WAPBLG": "",
"HRAEUPBG/WAPBLG/-Z": "languages",
"HRAPBG/WAPBLG/-Z": "",
"HRAEUPBG/WAPBLGZ": "languages",
"HRAPBG/WAPBLGZ": "",
"HRAEUPBG/WEURB": "languish",
"HRAPBG/WEURB": "",
"HRAEUPBG/WEURB/-D": "languished",
"HRAPBG/WEURB/-D": "",
"HRAEUPBG/WEURBD": "languished",
"HRAPBG/WEURBD": "",
"HRAEUPBG/WEUD": "languid",
"HRAPBG/WEUD": "",
"HRAEUPBG/O*R/KWRUS": "languorous",
"HRAEUPBG/RUS": "languorous",
"HA/RAEUPBG": "harangue",
"HA/RAEUPBGS": "harangues",
"HA/RAEUPBGD": "harangued",
"HA*EUPBG": "hank",
"HA*PBG": "",
"HA*EUPBG/KWRAOE": "hankie",
"HA*PBG/KWRAOE": "",
"HA*EUPBG/KWREU": "hanky",
"HA*PBG/KWREU": "",
"HA*EUPBG/*ER": "hanker",
"HA*PBG/*ER": "",
"HA*EUPBG/*ER/-G": "hankering",
"HA*PBG/*ER/-G": "",
"HA*EUPBG/*ERG": "hankering",
"HA*PBG/*ERG": "",
"HA*EUPBG/-D": "hanked",
"HA*PBG/-D": "",
"HA*EUPBG/-Z": "hanks",
"HA*PBG/-Z": "",
"HA*EUPBGD": "hanked",
"HA*PBGD": "",
"HA*EUPBGZ": "hanks",
"HA*PBGZ": "",
"HAEUPB/KAOE": "hankie",
"HAPB/KAOE": "",
"HAEUPB/KER/KHAOEF": "handkerchief",
"HAPB/KER/KHAOEF": "",
"HAEUPB/KER/KHEUF": "handkerchief",
"HAPB/KER/KHEUF": "",
"HAEUPBG/KAOE": "hankie",
"HAPBG/KAOE": "",
"HAEUPBG/KER/KHAOEF": "handkerchief",
"HAPBG/KER/KHAOEF": "",
"HAEUPBG/KER/KHEUF": "handkerchief",
"HAPBG/KER/KHEUF": "",
"HAEUPBG/A*R": "hangar",
"HAPBG/A*R": "",
"HAEUPBG/O*EFR": "hangover",
"HAPBG/O*EFR": "",
"HAEUPBG/O*UT": "hangout",
"HAPBG/O*UT": "",
"HAEUPBG/*ER": "hanger",
"HAPBG/*ER": "",
"HAEUPBG/*ER/-Z": "hangers",
"HAPBG/*ER/-Z": "",
"HAEUPBG/*ERZ": "hangers",
"HAPBG/*ERZ": "",
"HAEUPBG/-G": "hanging",
"HAPBG/-G": "",
"HAEUPBG/-G/WA*UL": "hangingwall",
"HAPBG/-G/WA*UL": "",
"HAEUPBG/-D": "hanged",
"HAPBG/-D": "",
"HAEUPBG/-Z": "hangs",
"HAPBG/-Z": "",
"HAEUPBGD": "hanged",
"HAPBGD": "",
"HAEUPBGZ": "hangs",
"HAPBGZ": "",
"HAEUPBG": "hang",
"HAPBG": "",
"HAEUPBG/TPHA*EUL": "hangnail",
"HAPBG/TPHA*EUL": "",
"HAEUPBG/KWROUT": "hangout",
"HAPBG/KWROUT": "",
"THAEUPBG": "thang",
"THAPBG": "",
"RA*EUPBG": "rank",
"RA*PBG": "",
"RA*EUPBG/HREU": "rankly",
"RA*PBG/HREU": "",
"RA*EUPBG/-L": "rankle",
"RA*PBG/-L": "",
"RA*EUPBG/-L/-G": "rankling",
"RA*PBG/-L/-G": "",
"RA*EUPBG/-L/-D": "rankled",
"RA*PBG/-L/-D": "",
"RA*EUPBG/-LG": "rankling",
"RA*PBG/-LG": "",
"RA*EUPBG/-LD": "rankled",
"RA*PBG/-LD": "",
"RA*EUPBG/-LZ": "rankles",
"RA*PBG/-LZ": "",
"RA*EUPBG/-G": "ranking",
"RA*PBG/-G": "",
"RA*EUPBG/-Z": "ranks",
"RA*PBG/-Z": "",
"RA*EUPBGD": "ranked",
"RA*PBGD": "",
"RA*EUPBGZ": "ranks",
"RA*PBGZ": "",
"RAEUPB/KOR": "rancor",
"RAPB/KOR": "",
"RAEUPB/KO/RUS": "rancorous",
"RAEUPB/KRUS": "rancorous",
"RAEUPBG/KOR": "rancor",
"RAPBG/KOR": "",
"RAEUPBG/KO/RUS": "rancorous",
"RAEUPBG/KRUS": "rancorous",
"REBG/TAEUPB/TKPWHRAR": "rectangular",
"REBG/TAPB/TKPWHRAR": "",
"REBG/TAEUPB/TKPWAOU/HRAR": "rectangular",
"REBG/TAPB/TKPWAOU/HRAR": "",
"REBG/TAEUPB/TKPW-L": "rectangle",
"REBG/TAPB/TKPW-L": "",
"REBG/TAEUPB/TKPW-L/-Z": "rectangles",
"REBG/TAPB/TKPW-L/-Z": "",
"REBG/TAEUPB/TKPW-LZ": "rectangles",
"REBG/TAPB/TKPW-LZ": "",
"REBG/TAEUPBG": "rectangle",
"REBG/TAPBG": "",
"REBG/TAEUPBG/TKPWHRAR": "rectangular",
"REBG/TAPBG/TKPWHRAR": "",
"REBG/TAEUPBG/TKPWAOU/HRAR": "rectangular",
"REBG/TAPBG/TKPWAOU/HRAR": "",
"REBG/TAEUPBG/TKPW-L": "rectangle",
"REBG/TAPBG/TKPW-L": "",
"REBG/TAEUPBG/TKPW-L/-Z": "rectangles",
"REBG/TAPBG/TKPW-L/-Z": "",
"REBG/TAEUPBG/TKPW-LZ": "rectangles",
"REBG/TAPBG/TKPW-LZ": "",
"REBG/TAEUPBG/HRAR": "rectangular",
"REBG/TAPBG/HRAR": "",
"REBG/TAEUPBG/-L": "rectangle",
"REBG/TAPBG/-L": "",
"REBG/TAEUPBG/-L/-Z": "rectangles",
"REBG/TAPBG/-L/-Z": "",
"REBG/TAEUPBG/-LZ": "rectangles",
"REBG/TAPBG/-LZ": "",
"A*EUPBG/KWREU/HROES": "ankylose",
"A*EUPBG/HROES": "ankylose",
"A*EUPBG/HROE/SEUS": "ankylosis",
"A*PBG/RAPBLG": "",
"A*EUPBG/-L": "ankle",
"A*PBG/-L": "",
"A*EUPBG/-L/-Z": "ankles",
"A*PBG/-L/-Z": "",
"A*EUPBG/-LT": "anklet",
"A*PBG/-LT": "",
"AEUPB/KHRET": "anklet",
"APB/KHRET": "",
"A*EUPBG/-LZ": "ankles",
"A*PBG/-LZ": "",
"A*EUPBGS": "angst",
"A*PBGS": "",
"AEUPBG/STROPL": "angstrom",
"APBG/STROPL": "",
"AEUPBG/SKWREU/KWRO/TKPWRAEF": "angiography",
"APBG/SKWREU/KWRO/TKPWRAEF": "",
"AEUPBG/SKWREU/KWRO/TKPWRAF/KWREU": "angiography",
"APBG/SKWREU/KWRO/TKPWRAF/KWREU": "",
"AEUPBG/SKWREU/KWROE/TKPWRAEF": "angiography",
"APBG/SKWREU/KWROE/TKPWRAEF": "",
"AEUPBG/SKWREU/KWROE/TKPWRAF/KWREU": "angiography",
"APBG/SKWREU/KWROE/TKPWRAF/KWREU": "",
"AEUPBG/SKWREU/KWRORG/TP*EU": "angiography",
"APBG/SKWREU/KWRORG/TP*EU": "",
"AEUPBG/SHUS": "anxious",
"APBG/SHUS": "",
"AEUPBG/SHUS/HREU": "anxiously",
"APBG/SHUS/HREU": "",
"AEUPBG/SAOEU/TEU": "anxiety",
"APBG/SAOEU/TEU": "",
"AEUPBG/SAOEU/KWRE/TEU": "anxiety",
"APBG/SAOEU/KWRE/TEU": "",
"AEUPBG/SAOEUT": "anxiety",
"APBG/SAOEUT": "",
"AEUPBG/TKPWAOU/HRAEUR/TEU": "angularity",
"APBG/TKPWAOU/HRAEUR/TEU": "",
"AEUPBG/TKPWAOU/HRAEURT": "angularity",
"APBG/TKPWAOU/HRAEURT": "",
"AEUPBG/TKPWAOU/HRAERT": "angularity",
"APBG/TKPWAOU/HRAERT": "",
"AEUPBG/TKPWAOU/HRAR/KWREU/TEU": "angularity",
"APBG/TKPWAOU/HRAR/KWREU/TEU": "",
"AEUPBG/TKPWOR/KWRA": "angora",
"APBG/TKPWOR/KWRA": "",
"AEUPBG/TKPWER": "anger",
"APBG/TKPWER": "",
"AEUPBG/TKPWER/-G": "angering",
"APBG/TKPWER/-G": "",
"AEUPBG/TKPWER/-Z": "angers",
"APBG/TKPWER/-Z": "",
"AEUPBG/TKPWERG": "angering",
"APBG/TKPWERG": "",
"AEUPBG/TKPWERZ": "angers",
"APBG/TKPWERZ": "",
"AEUPBG/TKPW-L": "angle",
"APBG/TKPW-L": "",
"AEUPBG/KPAOEU/TEU": "anxiety",
"APBG/KPAOEU/TEU": "",
"AEUPBG/KPAOEU/KWRE/TEU": "anxiety",
"APBG/KPAOEU/KWRE/TEU": "",
"AEUPBG/KPAOEUT": "anxiety",
"APBG/KPAOEUT": "",
"AEUPBG/KWRAOU/HRAEUR/KWREU/TEU": "angularity",
"APBG/KWRAOU/HRAEUR/KWREU/TEU": "",
"AEUPBG/KWRO/TKPWRAEF": "angiography",
"APBG/KWRO/TKPWRAEF": "",
"AEUPBG/KWRO/TKPWRAF/KWREU": "angiography",
"APBG/KWRO/TKPWRAF/KWREU": "",
"AEUPBG/KWROE/TKPWRAEF": "angiography",
"APBG/KWROE/TKPWRAEF": "",
"AEUPBG/KWROE/TKPWRAF/KWREU": "angiography",
"APBG/KWROE/TKPWRAF/KWREU": "",
"AEUPBG/KWROEG/TP*EU": "angiography",
"APBG/KWROEG/TP*EU": "",
"AEUPBG/KWROR/KWRA": "angora",
"APBG/KWROR/KWRA": "",
"AEUPBG/KWRORG/TP*EU": "angiography",
"APBG/KWRORG/TP*EU": "",
"AEUPBG/KWRER": "anger",
"APBG/KWRER": "",
"AEUPBG/KWRER/-G": "angering",
"APBG/KWRER/-G": "",
"AEUPBG/KWRER/-Z": "angers",
"APBG/KWRER/-Z": "",
"AEUPBG/KWRERG": "angering",
"APBG/KWRERG": "",
"AEUPBG/KWRERZ": "angers",
"APBG/KWRERZ": "",
"AEUPBG/KHOR": "anchor",
"APBG/KHOR": "",
"AEUPBG/KOR": "anchor",
"APBG/KOR": "",
"AEUPBG/K-L": "ankle",
"APBG/K-L": "",
"AEUPBG/WEURB": "anguish",
"APBG/WEURB": "",
"AEUPBG/WEURB/-D": "anguished",
"APBG/WEURB/-D": "",
"AEUPBG/WEURBD": "anguished",
"APBG/WEURBD": "",
"AEUPBG/HRAOEU": "anguli",
"APBG/HRAOEU": "",
"AEUPBG/HRAEURT": "angularity",
"APBG/HRAEURT": "",
"AEUPBG/HRAEUGS": "angulation",
"APBG/HRAEUGS": "",
"AEUPBG/HRAEUT": "angulate",
"APBG/HRAEUT": "",
"AEUPBG/HRAERT": "angularity",
"APBG/HRAERT": "",
"AEUPBG/HRAR": "angular",
"APBG/HRAR": "",
"AEUPBG/HRAR/TEU": "angularity",
"APBG/HRAR/TEU": "",
"AEUPBG/HRART": "angularity",
"APBG/HRART": "",
"AEUPBG/HREU": "anguli",
"APBG/HREU": "",
"AEUPBG/HREU/SAOEUGZ": "anglicizing",
"APBG/HREU/SAOEUGZ": "",
"AEUPBG/HREU/SAOEUSZ": "anglicizes",
"APBG/HREU/SAOEUSZ": "",
"AEUPBG/HREU/SAOEUDZ": "anglicized",
"APBG/HREU/SAOEUDZ": "",
"AEUPBG/HREU/SAOEUZ": "anglicize",
"APBG/HREU/SAOEUZ": "",
"AEUPBG/HREU/SAOEUZ/-D": "anglicized",
"APBG/HREU/SAOEUZ/-D": "",
"AEUPBG/HREUPBG": "angling",
"APBG/HREUPBG": "",
"APBG/HRER": "",
"AEUPBG/R*EU": "angri",
"APBG/R*EU": "",
"AEUPBG/REU": "angry",
"APBG/REU": "",
"AEUPBG/REU/KWREFT": "angriest",
"APBG/REU/KWREFT": "",
"AEUPBG/REU/HREU": "angrily",
"APBG/REU/HREU": "",
"AEUPBG/REU/*ER": "angrier",
"APBG/REU/*ER": "",
"AEUPBG/REU/-PBS": "angriness",
"APBG/REU/-PBS": "",
"AEUPBG/-RBS": "anxious",
"APBG/-RBS": "",
"AEUPBG/-RBS/HREU": "anxiously",
"APBG/-RBS/HREU": "",
"AEUPBG/-L": "angle",
"APBG/-L": "",
"AEUPBG/-L/-G": "angling",
"APBG/-L/-G": "",
"AEUPBG/-L/-D": "angled",
"APBG/-L/-D": "",
"AEUPBG/-L/-Z": "angles",
"APBG/-L/-Z": "",
"AEUPBG/-LG": "angling",
"APBG/-LG": "",
"AEUPBG/-LD": "angled",
"APBG/-LD": "",
"AEUPBG/-LZ": "angles",
"APBG/-LZ": "",
"AEUPBGS": "angst",
"APBGS": "",
"AEUPBGS/HREU": "anxiously",
"APBGS/HREU": "",
"AEUPB/KALZ": "ankles",
"APB/KALZ": "",
"APB/KOR": "",
"AEUPB/KOR/-D": "anchored",
"APB/KOR/-D": "",
"AEUPB/KOR/-Z": "anchors",
"APB/KOR/-Z": "",
"AEUPB/KORD": "anchored",
"APB/KORD": "",
"AEUPB/KORZ": "anchors",
"APB/KORZ": "",
"AEUPB/K-L": "ankle",
"APB/K-L": "",
"RAEPBG": "rang",
"RAPBG": "",
"RAEUPBG/TAEUPB": "orangutan",
"RAPBG/TAPB": "",
"OR/KWRAEUPB/TKPWAOU/TAEUPB": "orangutan",
"OR/KWRAPB/TKPWAOU/TAPB": "",
"OR/KWRAEUPBG/TKPWAOU/TAEUPB": "orangutan",
"OR/KWRAPBG/TKPWAOU/TAPB": "",
"OR/KWRAEUPBG/TAEUPB": "orangutan",
"OR/KWRAPBG/TAPB": "",
"OR/KWRAEUPBG/KWRAOU/TAEUPB": "orangutan",
"OR/KWRAPBG/KWRAOU/TAPB": "",
"WAEUPBG": "wang",
"TPAEUPBG": "fang",
"TPAPBG": "",
"TPAEUPBG/-Z": "fangs",
"TPAPBG/-Z": "",
"TPAEUPBGZ": "fangs",
"TPAPBGZ": "",
"PRAEUPBG": "prang",
"PRAPBG": ""
}
